vetariasn/__init__.py
vetariasn/_algo.py
vetariasn/_alock.py
vetariasn/_core.py
vetariasn/_orm.py
vetariasn/_queue.py
vetariasn-0.1.1.dist-info/LICENSE
vetariasn-0.1.1.dist-info/METADATA
vetariasn-0.1.1.dist-info/WHEEL
vetariasn-0.1.1.dist-info/top_level.txt
vetariasn-0.1.1.dist-info/RECORD
