Metadata-Version: 2.1
Name: vetariasn
Version: 0.1.1
Summary: Vetariasn: An new framework for developing great application
Author: lilingyi
Author-email: alan_sudo@yeah.net
License: The MIT License (MIT)
Requires: sqlalchemy
Requires: aiosqlite
Requires: fastapi
Requires: uvicorn
Requires: aiohttp
License-File: LICENSE
